{
    "sourceFile": "package.json",
    "activeCommit": 0,
    "commits": [
        {
            "activePatchIndex": 4,
            "patches": [
                {
                    "date": 1713165997449,
                    "content": "Index: \n===================================================================\n--- \n+++ \n"
                },
                {
                    "date": 1713166194492,
                    "content": "Index: \n===================================================================\n--- \n+++ \n@@ -0,0 +1,91 @@\n+{\n+  \"name\": \"canjobs\",\n+  \"version\": \"0.1.0\",\n+  \"private\": true,\n+  \"proxy\": \"https://apnaorganicstore.in\",\n+  \"dependencies\": {\n+    \"@emotion/styled\": \"^11.11.5\",\n+    \"@material-ui/core\": \"^5.0.0-beta.5\",\n+    \"@paypal/react-paypal-js\": \"^8.1.3\",\n+    \"@react-18-pdf/renderer\": \"^2.3.4\",\n+    \"@react-oauth/google\": \"^0.11.0\",\n+    \"@react-pdf-viewer/core\": \"^3.7.0\",\n+    \"@react-pdf/renderer\": \"^3.1.9\",\n+    \"@stripe/react-stripe-js\": \"^2.4.0\",\n+    \"@stripe/stripe-js\": \"^2.2.1\",\n+    \"@sweetalert/with-react\": \"^0.1.1\",\n+    \"@testing-library/jest-dom\": \"^5.16.5\",\n+    \"@testing-library/react\": \"^13.4.0\",\n+    \"@testing-library/user-event\": \"^13.5.0\",\n+    \"@tinymce/tinymce-react\": \"^4.3.2\",\n+    \"annotator\": \"^2.0.0-alpha.3\",\n+    \"apexcharts\": \"^3.46.0\",\n+    \"axios\": \"^1.6.5\",\n+    \"bootstrap\": \"^4.5.2\",\n+    \"braintree-web-drop-in\": \"^1.31.2\",\n+    \"ckeditor4-react\": \"^5.0.0\",\n+    \"draft-js\": \"^0.11.7\",\n+    \"draft-js-export-html\": \"^1.4.1\",\n+    \"fabric\": \"^5.3.0\",\n+    \"froala-editor\": \"^4.1.3\",\n+    \"gapi-script\": \"^1.2.0\",\n+    \"jwt-decode\": \"^3.1.2\",\n+    \"moment\": \"^2.29.4\",\n+    \"moment-timezone\": \"^0.5.45\",\n+    \"pspdfkit\": \"^2024.3.0\",\n+    \"react\": \"^18.2.0\",\n+    \"react-apexcharts\": \"^1.4.1\",\n+    \"react-bootstrap\": \"^2.7.2\",\n+    \"react-doc-viewer\": \"^0.1.5\",\n+    \"react-dom\": \"^18.2.0\",\n+    \"react-draft-wysiwyg\": \"^1.15.0\",\n+    \"react-facebook-login\": \"^4.1.1\",\n+    \"react-file-viewer\": \"^1.2.1\",\n+    \"react-froala-wysiwyg\": \"^4.1.3\",\n+    \"react-icons\": \"^4.10.1\",\n+    \"react-lazy-load\": \"^4.0.1\",\n+    \"react-linkedin-login-oauth2\": \"^2.0.1\",\n+    \"react-moment\": \"^1.1.3\",\n+    \"react-native-render-html\": \"^6.3.4\",\n+    \"react-native-web\": \"^0.19.4\",\n+    \"react-pdf\": \"^7.7.1\",\n+    \"react-pdf-js\": \"^5.1.0\",\n+    \"react-router-dom\": \"^6.8.1\",\n+    \"react-scripts\": \"^2.1.3\",\n+    \"react-select\": \"^5.7.2\",\n+    \"react-select-search\": \"^4.1.6\",\n+    \"react-spinners\": \"^0.13.8\",\n+    \"react-toastify\": \"^8.0.0\",\n+    \"resolve-url\": \"^0.2.1\",\n+    \"sweetalert\": \"^1.1.2\",\n+    \"sweetalert-react\": \"^0.4.10\",\n+    \"web-vitals\": \"^2.1.4\"\n+  },\n+  \"scripts\": {\n+    \"start\": \"react-scripts start\",\n+    \"build\": \"react-scripts --max_old_space_size=9096 build\",\n+    \"test\": \"react-scripts test\",\n+    \"eject\": \"react-scripts eject\"\n+  },\n+  \"eslintConfig\": {\n+    \"extends\": [\n+      \"react-app\",\n+      \"react-app/jest\"\n+    ]\n+  },\n+  \"browserslist\": {\n+    \"production\": [\n+      \">0.2%\",\n+      \"not dead\",\n+      \"not op_mini all\"\n+    ],\n+    \"development\": [\n+      \"last 1 chrome version\",\n+      \"last 1 firefox version\",\n+      \"last 1 safari version\"\n+    ]\n+  },\n+  \"devDependencies\": {\n+    \"@babel/preset-react\": \"^7.22.15\"\n+  }\n+}\n\\ No newline at end of file\n"
                },
                {
                    "date": 1713166273051,
                    "content": "Index: \n===================================================================\n--- \n+++ \n@@ -31,9 +31,8 @@\n     \"gapi-script\": \"^1.2.0\",\n     \"jwt-decode\": \"^3.1.2\",\n     \"moment\": \"^2.29.4\",\n     \"moment-timezone\": \"^0.5.45\",\n-    \"pspdfkit\": \"^2024.3.0\",\n     \"react\": \"^18.2.0\",\n     \"react-apexcharts\": \"^1.4.1\",\n     \"react-bootstrap\": \"^2.7.2\",\n     \"react-doc-viewer\": \"^0.1.5\",\n@@ -62,9 +61,9 @@\n     \"web-vitals\": \"^2.1.4\"\n   },\n   \"scripts\": {\n     \"start\": \"react-scripts start\",\n-    \"build\": \"react-scripts --max_old_space_size=9096 build\",\n+    \"build\": \"react-scripts --max_old_space_size=4096 build\",\n     \"test\": \"react-scripts test\",\n     \"eject\": \"react-scripts eject\"\n   },\n   \"eslintConfig\": {\n@@ -87,5 +86,5 @@\n   },\n   \"devDependencies\": {\n     \"@babel/preset-react\": \"^7.22.15\"\n   }\n-}\n\\ No newline at end of file\n+}\n"
                },
                {
                    "date": 1713169994341,
                    "content": "Index: \n===================================================================\n--- \n+++ \n@@ -31,98 +31,8 @@\n     \"gapi-script\": \"^1.2.0\",\n     \"jwt-decode\": \"^3.1.2\",\n     \"moment\": \"^2.29.4\",\n     \"moment-timezone\": \"^0.5.45\",\n-    \"react\": \"^18.2.0\",\n-    \"react-apexcharts\": \"^1.4.1\",\n-    \"react-bootstrap\": \"^2.7.2\",\n-    \"react-doc-viewer\": \"^0.1.5\",\n-    \"react-dom\": \"^18.2.0\",\n-    \"react-draft-wysiwyg\": \"^1.15.0\",\n-    \"react-facebook-login\": \"^4.1.1\",\n-    \"react-file-viewer\": \"^1.2.1\",\n-    \"react-froala-wysiwyg\": \"^4.1.3\",\n-    \"react-icons\": \"^4.10.1\",\n-    \"react-lazy-load\": \"^4.0.1\",\n-    \"react-linkedin-login-oauth2\": \"^2.0.1\",\n-    \"react-moment\": \"^1.1.3\",\n-    \"react-native-render-html\": \"^6.3.4\",\n-    \"react-native-web\": \"^0.19.4\",\n-    \"react-pdf\": \"^7.7.1\",\n-    \"react-pdf-js\": \"^5.1.0\",\n-    \"react-router-dom\": \"^6.8.1\",\n-    \"react-scripts\": \"^2.1.3\",\n-    \"react-select\": \"^5.7.2\",\n-    \"react-select-search\": \"^4.1.6\",\n-    \"react-spinners\": \"^0.13.8\",\n-    \"react-toastify\": \"^8.0.0\",\n-    \"resolve-url\": \"^0.2.1\",\n-    \"sweetalert\": \"^1.1.2\",\n-    \"sweetalert-react\": \"^0.4.10\",\n-    \"web-vitals\": \"^2.1.4\"\n-  },\n-  \"scripts\": {\n-    \"start\": \"react-scripts start\",\n-    \"build\": \"react-scripts --max_old_space_size=4096 build\",\n-    \"test\": \"react-scripts test\",\n-    \"eject\": \"react-scripts eject\"\n-  },\n-  \"eslintConfig\": {\n-    \"extends\": [\n-      \"react-app\",\n-      \"react-app/jest\"\n-    ]\n-  },\n-  \"browserslist\": {\n-    \"production\": [\n-      \">0.2%\",\n-      \"not dead\",\n-      \"not op_mini all\"\n-    ],\n-    \"development\": [\n-      \"last 1 chrome version\",\n-      \"last 1 firefox version\",\n-      \"last 1 safari version\"\n-    ]\n-  },\n-  \"devDependencies\": {\n-    \"@babel/preset-react\": \"^7.22.15\"\n-  }\n-}\n-{\n-  \"name\": \"canjobs\",\n-  \"version\": \"0.1.0\",\n-  \"private\": true,\n-  \"proxy\": \"https://apnaorganicstore.in\",\n-  \"dependencies\": {\n-    \"@emotion/styled\": \"^11.11.5\",\n-    \"@material-ui/core\": \"^5.0.0-beta.5\",\n-    \"@paypal/react-paypal-js\": \"^8.1.3\",\n-    \"@react-18-pdf/renderer\": \"^2.3.4\",\n-    \"@react-oauth/google\": \"^0.11.0\",\n-    \"@react-pdf-viewer/core\": \"^3.7.0\",\n-    \"@react-pdf/renderer\": \"^3.1.9\",\n-    \"@stripe/react-stripe-js\": \"^2.4.0\",\n-    \"@stripe/stripe-js\": \"^2.2.1\",\n-    \"@sweetalert/with-react\": \"^0.1.1\",\n-    \"@testing-library/jest-dom\": \"^5.16.5\",\n-    \"@testing-library/react\": \"^13.4.0\",\n-    \"@testing-library/user-event\": \"^13.5.0\",\n-    \"@tinymce/tinymce-react\": \"^4.3.2\",\n-    \"annotator\": \"^2.0.0-alpha.3\",\n-    \"apexcharts\": \"^3.46.0\",\n-    \"axios\": \"^1.6.5\",\n-    \"bootstrap\": \"^4.5.2\",\n-    \"braintree-web-drop-in\": \"^1.31.2\",\n-    \"ckeditor4-react\": \"^5.0.0\",\n-    \"draft-js\": \"^0.11.7\",\n-    \"draft-js-export-html\": \"^1.4.1\",\n-    \"fabric\": \"^5.3.0\",\n-    \"froala-editor\": \"^4.1.3\",\n-    \"gapi-script\": \"^1.2.0\",\n-    \"jwt-decode\": \"^3.1.2\",\n-    \"moment\": \"^2.29.4\",\n-    \"moment-timezone\": \"^0.5.45\",\n     \"pspdfkit\": \"^2024.3.0\",\n     \"react\": \"^18.2.0\",\n     \"react-apexcharts\": \"^1.4.1\",\n     \"react-bootstrap\": \"^2.7.2\",\n@@ -151,10 +61,10 @@\n     \"sweetalert-react\": \"^0.4.10\",\n     \"web-vitals\": \"^2.1.4\"\n   },\n   \"scripts\": {\n-    \"start\": \"react-scripts start\",\n-    \"build\": \"react-scripts --max_old_space_size=9096 build\",\n+    \"start\": \"node --max-old-space-size=4096 node_modules/react-scripts/scripts/start.js\",\n+    \"build\": \"node --max-old-space-size=4096 node_modules/react-scripts/scripts/build.js\",\n     \"test\": \"react-scripts test\",\n     \"eject\": \"react-scripts eject\"\n   },\n   \"eslintConfig\": {\n@@ -177,5 +87,5 @@\n   },\n   \"devDependencies\": {\n     \"@babel/preset-react\": \"^7.22.15\"\n   }\n-}\n+}\n\\ No newline at end of file\n"
                },
                {
                    "date": 1713240943019,
                    "content": "Index: \n===================================================================\n--- \n+++ \n@@ -1,70 +1,36 @@\n {\n   \"name\": \"canjobs\",\n   \"version\": \"0.1.0\",\n   \"private\": true,\n-  \"proxy\": \"https://apnaorganicstore.in\",\n+  \"proxy\": \"https://apnaorganicstore.in/canjobs/\",\n   \"dependencies\": {\n-    \"@emotion/styled\": \"^11.11.5\",\n-    \"@material-ui/core\": \"^5.0.0-beta.5\",\n-    \"@paypal/react-paypal-js\": \"^8.1.3\",\n     \"@react-18-pdf/renderer\": \"^2.3.4\",\n-    \"@react-oauth/google\": \"^0.11.0\",\n-    \"@react-pdf-viewer/core\": \"^3.7.0\",\n     \"@react-pdf/renderer\": \"^3.1.9\",\n-    \"@stripe/react-stripe-js\": \"^2.4.0\",\n-    \"@stripe/stripe-js\": \"^2.2.1\",\n     \"@sweetalert/with-react\": \"^0.1.1\",\n     \"@testing-library/jest-dom\": \"^5.16.5\",\n     \"@testing-library/react\": \"^13.4.0\",\n     \"@testing-library/user-event\": \"^13.5.0\",\n-    \"@tinymce/tinymce-react\": \"^4.3.2\",\n-    \"annotator\": \"^2.0.0-alpha.3\",\n-    \"apexcharts\": \"^3.46.0\",\n-    \"axios\": \"^1.6.5\",\n+    \"axios\": \"^1.3.4\",\n     \"bootstrap\": \"^4.5.2\",\n-    \"braintree-web-drop-in\": \"^1.31.2\",\n-    \"ckeditor4-react\": \"^5.0.0\",\n-    \"draft-js\": \"^0.11.7\",\n-    \"draft-js-export-html\": \"^1.4.1\",\n-    \"fabric\": \"^5.3.0\",\n-    \"froala-editor\": \"^4.1.3\",\n-    \"gapi-script\": \"^1.2.0\",\n-    \"jwt-decode\": \"^3.1.2\",\n     \"moment\": \"^2.29.4\",\n-    \"moment-timezone\": \"^0.5.45\",\n-    \"pspdfkit\": \"^2024.3.0\",\n     \"react\": \"^18.2.0\",\n-    \"react-apexcharts\": \"^1.4.1\",\n     \"react-bootstrap\": \"^2.7.2\",\n-    \"react-doc-viewer\": \"^0.1.5\",\n     \"react-dom\": \"^18.2.0\",\n-    \"react-draft-wysiwyg\": \"^1.15.0\",\n-    \"react-facebook-login\": \"^4.1.1\",\n-    \"react-file-viewer\": \"^1.2.1\",\n-    \"react-froala-wysiwyg\": \"^4.1.3\",\n-    \"react-icons\": \"^4.10.1\",\n-    \"react-lazy-load\": \"^4.0.1\",\n-    \"react-linkedin-login-oauth2\": \"^2.0.1\",\n     \"react-moment\": \"^1.1.3\",\n-    \"react-native-render-html\": \"^6.3.4\",\n-    \"react-native-web\": \"^0.19.4\",\n-    \"react-pdf\": \"^7.7.1\",\n-    \"react-pdf-js\": \"^5.1.0\",\n     \"react-router-dom\": \"^6.8.1\",\n     \"react-scripts\": \"^2.1.3\",\n     \"react-select\": \"^5.7.2\",\n     \"react-select-search\": \"^4.1.6\",\n-    \"react-spinners\": \"^0.13.8\",\n     \"react-toastify\": \"^8.0.0\",\n     \"resolve-url\": \"^0.2.1\",\n     \"sweetalert\": \"^1.1.2\",\n     \"sweetalert-react\": \"^0.4.10\",\n     \"web-vitals\": \"^2.1.4\"\n   },\n   \"scripts\": {\n-    \"start\": \"node --max-old-space-size=4096 node_modules/react-scripts/scripts/start.js\",\n-    \"build\": \"node --max-old-space-size=4096 node_modules/react-scripts/scripts/build.js\",\n+    \"start\": \"react-scripts start\",\n+    \"build\": \"react-scripts build\",\n     \"test\": \"react-scripts test\",\n     \"eject\": \"react-scripts eject\"\n   },\n   \"eslintConfig\": {\n@@ -84,8 +50,8 @@\n       \"last 1 firefox version\",\n       \"last 1 safari version\"\n     ]\n   },\n-  \"devDependencies\": {\n-    \"@babel/preset-react\": \"^7.22.15\"\n-  }\n+  \"presets\": [\n+    \"@babel/preset-env\"\n+  ]\n }\n\\ No newline at end of file\n"
                }
            ],
            "date": 1713165997449,
            "name": "Commit-0",
            "content": "{\n  \"name\": \"canjobs\",\n  \"version\": \"0.1.0\",\n  \"private\": true,\n  \"proxy\": \"https://apnaorganicstore.in\",\n  \"dependencies\": {\n    \"@emotion/styled\": \"^11.11.5\",\n    \"@material-ui/core\": \"^5.0.0-beta.5\",\n    \"@paypal/react-paypal-js\": \"^8.1.3\",\n    \"@react-18-pdf/renderer\": \"^2.3.4\",\n    \"@react-oauth/google\": \"^0.11.0\",\n    \"@react-pdf-viewer/core\": \"^3.7.0\",\n    \"@react-pdf/renderer\": \"^3.1.9\",\n    \"@stripe/react-stripe-js\": \"^2.4.0\",\n    \"@stripe/stripe-js\": \"^2.2.1\",\n    \"@sweetalert/with-react\": \"^0.1.1\",\n    \"@testing-library/jest-dom\": \"^5.16.5\",\n    \"@testing-library/react\": \"^13.4.0\",\n    \"@testing-library/user-event\": \"^13.5.0\",\n    \"@tinymce/tinymce-react\": \"^4.3.2\",\n    \"annotator\": \"^2.0.0-alpha.3\",\n    \"apexcharts\": \"^3.46.0\",\n    \"axios\": \"^1.6.5\",\n    \"bootstrap\": \"^4.5.2\",\n    \"braintree-web-drop-in\": \"^1.31.2\",\n    \"ckeditor4-react\": \"^5.0.0\",\n    \"draft-js\": \"^0.11.7\",\n    \"draft-js-export-html\": \"^1.4.1\",\n    \"fabric\": \"^5.3.0\",\n    \"froala-editor\": \"^4.1.3\",\n    \"gapi-script\": \"^1.2.0\",\n    \"jwt-decode\": \"^3.1.2\",\n    \"moment\": \"^2.29.4\",\n    \"moment-timezone\": \"^0.5.45\",\n    \"pspdfkit\": \"^2024.3.0\",\n    \"react\": \"^18.2.0\",\n    \"react-apexcharts\": \"^1.4.1\",\n    \"react-bootstrap\": \"^2.7.2\",\n    \"react-doc-viewer\": \"^0.1.5\",\n    \"react-dom\": \"^18.2.0\",\n    \"react-draft-wysiwyg\": \"^1.15.0\",\n    \"react-facebook-login\": \"^4.1.1\",\n    \"react-file-viewer\": \"^1.2.1\",\n    \"react-froala-wysiwyg\": \"^4.1.3\",\n    \"react-icons\": \"^4.10.1\",\n    \"react-lazy-load\": \"^4.0.1\",\n    \"react-linkedin-login-oauth2\": \"^2.0.1\",\n    \"react-moment\": \"^1.1.3\",\n    \"react-native-render-html\": \"^6.3.4\",\n    \"react-native-web\": \"^0.19.4\",\n    \"react-pdf\": \"^7.7.1\",\n    \"react-pdf-js\": \"^5.1.0\",\n    \"react-router-dom\": \"^6.8.1\",\n    \"react-scripts\": \"^2.1.3\",\n    \"react-select\": \"^5.7.2\",\n    \"react-select-search\": \"^4.1.6\",\n    \"react-spinners\": \"^0.13.8\",\n    \"react-toastify\": \"^8.0.0\",\n    \"resolve-url\": \"^0.2.1\",\n    \"sweetalert\": \"^1.1.2\",\n    \"sweetalert-react\": \"^0.4.10\",\n    \"web-vitals\": \"^2.1.4\"\n  },\n  \"scripts\": {\n    \"start\": \"react-scripts start\",\n    \"build\": \"react-scripts --max_old_space_size=9096 build\",\n    \"test\": \"react-scripts test\",\n    \"eject\": \"react-scripts eject\"\n  },\n  \"eslintConfig\": {\n    \"extends\": [\n      \"react-app\",\n      \"react-app/jest\"\n    ]\n  },\n  \"browserslist\": {\n    \"production\": [\n      \">0.2%\",\n      \"not dead\",\n      \"not op_mini all\"\n    ],\n    \"development\": [\n      \"last 1 chrome version\",\n      \"last 1 firefox version\",\n      \"last 1 safari version\"\n    ]\n  },\n  \"devDependencies\": {\n    \"@babel/preset-react\": \"^7.22.15\"\n  }\n}\n"
        }
    ]
}